Bohrium_Pygments_Lexer-0.0.1.dist-info/DESCRIPTION.rst
Bohrium_Pygments_Lexer-0.0.1.dist-info/METADATA
Bohrium_Pygments_Lexer-0.0.1.dist-info/RECORD
Bohrium_Pygments_Lexer-0.0.1.dist-info/WHEEL
Bohrium_Pygments_Lexer-0.0.1.dist-info/entry_points.txt
Bohrium_Pygments_Lexer-0.0.1.dist-info/metadata.json
Bohrium_Pygments_Lexer-0.0.1.dist-info/top_level.txt
bohrium_lexer/__init__.py
