Metadata-Version: 2.0
Name: Bohrium-Pygments-Lexer
Version: 0.0.1
Summary: Bohrium Pygments Lexer
Home-page: https://github.com/bh107/bohrium_pygments_lexer
Author: Mads Ohm Larsen
Author-email: ohm@nbi.ku.dk
License: GPL
Platform: UNKNOWN
Requires-Dist: pygments (>=2.0.2)
